pycoolmasternet/__init__.py
pycoolmasternet-0.0.2.dist-info/DESCRIPTION.rst
pycoolmasternet-0.0.2.dist-info/METADATA
pycoolmasternet-0.0.2.dist-info/RECORD
pycoolmasternet-0.0.2.dist-info/WHEEL
pycoolmasternet-0.0.2.dist-info/metadata.json
pycoolmasternet-0.0.2.dist-info/top_level.txt
pycoolmasternet-0.0.2.dist-info/zip-safe
