Metadata-Version: 2.0
Name: pycoolmasternet
Version: 0.0.2
Summary: Lightweight Python API for CoolMasterNet HVAC bridges
Home-page: http://github.com/koreth/pycoolmasternet
Author: Steven Grimm
Author-email: koreth@gmail.com
License: MIT
Keywords: hvac homeautomation
Platform: UNKNOWN
Classifier: Development Status :: 3 - Alpha
Classifier: License :: OSI Approved :: MIT License
Classifier: Operating System :: OS Independent
Classifier: Programming Language :: Python
Classifier: Programming Language :: Python :: 2.7
Classifier: Programming Language :: Python :: 3.5
Classifier: Topic :: Home Automation
Classifier: Topic :: Software Development :: Libraries :: Python Modules
